venus_tempest_plugin/__init__.py
venus_tempest_plugin/config.py
venus_tempest_plugin/plugin.py
venus_tempest_plugin/services/__init__.py
venus_tempest_plugin/services/venus_rest_client.py
venus_tempest_plugin/tests/__init__.py
venus_tempest_plugin/tests/api/__init__.py
venus_tempest_plugin/tests/api/base.py
venus_tempest_plugin/tests/api/test_versions.py
venus_tempest_plugin/tests/scenario/__init__.py
venus_tempest_plugin-3.5.0.dist-info/AUTHORS
venus_tempest_plugin-3.5.0.dist-info/LICENSE
venus_tempest_plugin-3.5.0.dist-info/METADATA
venus_tempest_plugin-3.5.0.dist-info/WHEEL
venus_tempest_plugin-3.5.0.dist-info/entry_points.txt
venus_tempest_plugin-3.5.0.dist-info/pbr.json
venus_tempest_plugin-3.5.0.dist-info/top_level.txt
venus_tempest_plugin-3.5.0.dist-info/RECORD
