Metadata-Version: 2.1
Name: venus-tempest-plugin
Version: 3.5.0
Summary: OpenStack Log Management Service Tempest Plugin
Home-page: http://www.openstack.org/
Author: OpenStack
Author-email: openstack-discuss@lists.openstack.org
Keywords: setup,distutils
Classifier: Environment :: OpenStack
Classifier: Intended Audience :: Information Technology
Classifier: Intended Audience :: System Administrators
Classifier: License :: OSI Approved :: Apache Software License
Classifier: Operating System :: POSIX :: Linux
Classifier: Programming Language :: Python
Classifier: Programming Language :: Python :: Implementation :: CPython
Classifier: Programming Language :: Python :: 3 :: Only
Classifier: Programming Language :: Python :: 3
Classifier: Programming Language :: Python :: 3.9
Classifier: Programming Language :: Python :: 3.10
Classifier: Programming Language :: Python :: 3.11
Classifier: Programming Language :: Python :: 3.12
Requires-Python: >=3.9
License-File: LICENSE
License-File: AUTHORS
Requires-Dist: pbr !=2.1.0,>=2.0.0
Requires-Dist: oslo.config >=5.2.0
Requires-Dist: oslo.serialization !=2.19.1,>=2.18.0
Requires-Dist: oslo.utils >=3.33.0
Requires-Dist: testtools >=2.4.0
Requires-Dist: testscenarios >=0.4
Requires-Dist: tempest >=27.0.0
Requires-Dist: requests >=2.14.2
